vxapprouter/__init__.py
vxapprouter/router.py
vxapprouter-0.4.0.dist-info/top_level.txt
vxapprouter-0.4.0.dist-info/METADATA
vxapprouter-0.4.0.dist-info/DESCRIPTION.rst
vxapprouter-0.4.0.dist-info/metadata.json
vxapprouter-0.4.0.dist-info/WHEEL
vxapprouter-0.4.0.dist-info/RECORD
