Metadata-Version: 2.0
Name: vxapprouter
Version: 0.4.0
Summary: This is the Vumi Application Router project.
Home-page: https://github.com/smn/vumi-app-router
Author: Praekelt Foundation
Author-email: dev@praekeltfoundation.org
License: BSD
Keywords: vxapprouter
Platform: UNKNOWN
Classifier: Intended Audience :: Developers
Classifier: Natural Language :: English
Classifier: Programming Language :: Python :: 2.7
Requires-Dist: vumi
